setup.py
noML/__init__.py
noML/noML.py
noML.egg-info/PKG-INFO
noML.egg-info/SOURCES.txt
noML.egg-info/dependency_links.txt
noML.egg-info/not-zip-safe
noML.egg-info/top_level.txt