Metadata-Version: 1.0
Name: noML
Version: 0.1
Summary: For making ML learning like piece of cake for anyone :)
Home-page: UNKNOWN
Author: Rushikesh Darge
Author-email: UNKNOWN
License: UNKNOWN
Platform: UNKNOWN
